LICENSE
invincible/__init__.py
invincible/__main__.py
invincible/main.py
invincible-0.0.3.dist-info/entry_points.txt
invincible-0.0.3.dist-info/LICENSE
invincible-0.0.3.dist-info/WHEEL
invincible-0.0.3.dist-info/METADATA
invincible-0.0.3.dist-info/RECORD
